setup.py
client/__init__.py
client/client.py
client/client/__init__.py
client/client/add_contact.py
client/client/chat_window.py
client/client/client_d_b.py
client/client/client_oop.py
client/client/del_contact.py
client/client/list_client_window.py
client/client/main_chat.py
client/client/main_window.py
client/client/start_dialog.py
client/common/__init__.py
client/common/meta.py
client/common/my_func.py
client/common/wrapper.py
client/log/__init__.py
client/log/client_log_config.py
client/log/server_log_config.py
client/log/wrapp_log_config.py
client_proj_dav.egg-info/PKG-INFO
client_proj_dav.egg-info/SOURCES.txt
client_proj_dav.egg-info/dependency_links.txt
client_proj_dav.egg-info/requires.txt
client_proj_dav.egg-info/top_level.txt