Metadata-Version: 2.1
Name: client-proj-dav
Version: 0.0.1
Summary: Client packet
Home-page: UNKNOWN
Author: Konstantuan
Author-email: dakope@tut.by
License: UNKNOWN
Platform: UNKNOWN
